{
  "01" : {
    "name": "Chronal Calibration",
    "part1": 87430,
    "part2": 68189
  },
  "02": {
    "name": "",
    "part1": "",
    "part2": ""
  },
  "03": {
    "name": "",
    "part1": "",
    "part2": ""
  },
  "04": {
    "name": "",
    "part1": "",
    "part2": ""
  },
  "05": {
    "name": "",
    "part1": "",
    "part2": ""
  },
  "06": {
    "name": "",
    "part1": "",
    "part2": ""
  },
  "07": {
    "name": "",
    "part1": "",
    "part2": ""
  },
  "08": {
    "name": "",
    "part1": "",
    "part2": ""
  },
  "09": {
    "name": "",
    "part1": "",
    "part2": ""
  },
  "10": {
    "name": "",
    "part1": "",
    "part2": ""
  }, 
  "11": {
    "name": "",
    "part1": "",
    "part2": ""
  },
  "12": {
    "name": "",
    "part1": "",
    "part2": ""
  },
  "13": {
    "name": "",
    "part1": "",
    "part2": ""
  },
  "14": {
    "name": "",
    "part1": "",
    "part2": ""
  },
  "15": {
    "name": "",
    "part1": "",
    "part2": ""
  },
  "16": {
    "name": "",
    "part1": "",
    "part2": ""
  },
  "17": {
    "name": "",
    "part1": "",
    "part2": ""
  },
  "18": {
    "name": "",
    "part1": "",
    "part2": ""
  },
  "19": {
    "name": "",
    "part1": "",
    "part2": ""
  },
  "20": {
    "name": "",
    "part1": "",
    "part2": ""
  },
  "21": {
    "name": "",
    "part1": "",
    "part2": ""
  },
  "22": {
    "name": "",
    "part1": "",
    "part2": ""
  },
  "23": {
    "name": "",
    "part1": "",
    "part2": ""
  },
  "24": {
    "name": "",
    "part1": "",
    "part2": ""
  },
  "25": {
    "name": "",
    "part1": "",
    "part2": ""
  }
}